[
  {
    "key": "usa--tornado--wisconsin-dane-county",
    "source": "NOAA NWS Extreme",
    "ts": 1779034849
  },
  {
    "key": "philippines--quake--maguindanao-del-sur",
    "source": "GN: Earthquake",
    "ts": 1779034849
  },
  {
    "key": "usa--fire--chino-hills-california",
    "source": "GN: Wildfire",
    "ts": 1779034851
  },
  {
    "key": "thailand--crash--bangkok-rail",
    "source": "Sky News",
    "ts": 1779034851
  },
  {
    "key": "uae--attack--barakah-power-plant",
    "source": "GN: Terror Attack",
    "ts": 1779035453
  },
  {
    "key": "usa--tornado-warning--wisconsin",
    "source": "NOAA NWS Extreme",
    "ts": 1779035453
  },
  {
    "key": "usa--crash--phoenix",
    "source": "GN: Breaking News",
    "ts": 1779035453
  },
  {
    "key": "palestinian-territories--airstrike--gaza",
    "source": "GN: Strike Attack",
    "ts": 1779035453
  },
  {
    "key": "caribbean--quake--eastern",
    "source": "GN: Earthquake",
    "ts": 1779035453
  },
  {
    "key": "lebanon--drone-strike--jebchit",
    "source": "TG: WarMonitors",
    "ts": 1779036049
  },
  {
    "key": "china--quake--liuzhou",
    "source": "USGS Quakes M4.5+",
    "ts": 1779036049
  },
  {
    "key": "usa--tornado--wisconsin",
    "source": "NOAA NWS Extreme",
    "ts": 1779036052
  },
  {
    "key": "mexico--attack--puebla",
    "source": "GN: Breaking News",
    "ts": 1779036052
  },
  {
    "key": "bolivia--protest--lapaz",
    "source": "France 24 Intl",
    "ts": 1779036055
  },
  {
    "key": "usa--quake--hollister",
    "source": "GN: Earthquake",
    "ts": 1779036056
  },
  {
    "key": "drc--ebola--northeast",
    "source": "Al Jazeera",
    "ts": 1779036056
  },
  {
    "key": "trusted-trump-says-irans-running-out",
    "source": "TG: Faytuks Network",
    "ts": 1779036515
  },
  {
    "key": "trusted-trump-says-iran-better-get",
    "source": "X: @Osinttechnical",
    "ts": 1779036582
  },
  {
    "key": "trusted-via-ukraines-1st-uas-center",
    "source": "X: @Osinttechnical",
    "ts": 1779036585
  },
  {
    "key": "trusted-strike-location-453260277-329912111-httpstcoxvs5drwk",
    "source": "X: @Osinttechnical",
    "ts": 1779036587
  },
  {
    "key": "trusted-onboard-footage-from-ukrainian-fp2",
    "source": "X: @Osinttechnical",
    "ts": 1779036590
  },
  {
    "key": "gaza--attack--gaza",
    "source": "Al Jazeera",
    "ts": 1779036648
  },
  {
    "key": "gaza--airstrike--gaza",
    "source": "GN: Strike Attack",
    "ts": 1779036648
  },
  {
    "key": "trusted-additional-footage-russian-forces-started",
    "source": "X: @Osinttechnical",
    "ts": 1779036936
  },
  {
    "key": "global--ebola--emergency-declaration",
    "source": "GN: CNN",
    "ts": 1779037254
  },
  {
    "key": "global--ebola--emergency-declaration",
    "source": "GN: Outbreak",
    "ts": 1779037257
  },
  {
    "key": "lebanon--airstrike--nationwide",
    "source": "GN: Strike Attack",
    "ts": 1779037259
  },
  {
    "key": "canada--hantavirus--cruise-ship",
    "source": "GN: CNN",
    "ts": 1779037259
  },
  {
    "key": "gaza--airstrike--hamas-commander",
    "source": "GN: Strike Attack",
    "ts": 1779037259
  },
  {
    "key": "congo--outbreak--ebola",
    "source": "GN: Outbreak",
    "ts": 1779037850
  },
  {
    "key": "palestine--airstrike--gaza",
    "source": "GN: Strike Attack",
    "ts": 1779037850
  },
  {
    "key": "congo--outbreak--ebola",
    "source": "GN: Outbreak",
    "ts": 1779037850
  },
  {
    "key": "usa--quake--nevada",
    "source": "GN: Earthquake",
    "ts": 1779037850
  },
  {
    "key": "lebanon--explosion--south",
    "source": "GN: Explosion",
    "ts": 1779037850
  },
  {
    "key": "gaza--airstrike--unspecified",
    "source": "GN: Reuters",
    "ts": 1779037850
  }
]