[
  {
    "key": "ukraine--airstrike--kyiv",
    "source": "Guardian World",
    "ts": 1778835059
  },
  {
    "key": "russia-ukraine--prisoner-exchange--uae-mediated",
    "source": "TASS English",
    "ts": 1778835059
  },
  {
    "key": "usa--quake--lake-county-california",
    "source": "GN: Earthquake",
    "ts": 1778835064
  },
  {
    "key": "usa--explosion--los-angeles",
    "source": "GN: Explosion",
    "ts": 1778835064
  },
  {
    "key": "congo--outbreak--ebola",
    "source": "GN: AP News",
    "ts": 1778835064
  },
  {
    "key": "ukraine--missile-strike--kyiv",
    "source": "GN: Strike Attack",
    "ts": 1778835660
  },
  {
    "key": "ukraine--missile-strike--kyiv",
    "source": "Straits Times World",
    "ts": 1778835660
  },
  {
    "key": "congo--outbreak--ebola",
    "source": "CBS News World",
    "ts": 1778836255
  },
  {
    "key": "congo--outbreak--ebola",
    "source": "GN: Outbreak",
    "ts": 1778836255
  },
  {
    "key": "none",
    "source": "GN: CNN",
    "ts": 1778836255
  },
  {
    "key": "ukraine--missile-strike--kyiv",
    "source": "GN: Strike Attack",
    "ts": 1778836258
  },
  {
    "key": "india--hostage--manipur",
    "source": "GN: Hostage",
    "ts": 1778836849
  },
  {
    "key": "ukraine--strike--sumy",
    "source": "TASS English",
    "ts": 1778836849
  },
  {
    "key": "usa--explosion--miami",
    "source": "GN: Explosion",
    "ts": 1778836849
  },
  {
    "key": "iraq--explosion--erbil",
    "source": "GN: Explosion",
    "ts": 1778836849
  },
  {
    "key": "ukraine--missile-strike--kyiv",
    "source": "GN: Strike Attack",
    "ts": 1778836849
  },
  {
    "key": "ukraine--airstrike--kyiv",
    "source": "GN: Strike Attack",
    "ts": 1778836849
  },
  {
    "key": "lebanon--airstrike--burj-al-shamali",
    "source": "TG: WarMonitors",
    "ts": 1778837458
  },
  {
    "key": "sudan--famine-risk--food-insecurity",
    "source": "ReliefWeb Updates",
    "ts": 1778837458
  },
  {
    "key": "drc--outbreak--ebola",
    "source": "GN: Outbreak",
    "ts": 1778837459
  },
  {
    "key": "usa--storm--up",
    "source": "GN: Breaking News",
    "ts": 1778837459
  },
  {
    "key": "haiti--gang-clashes--port-au-prince",
    "source": "France 24 Intl",
    "ts": 1778838051
  },
  {
    "key": "ukraine--missile-strike--kyiv",
    "source": "NPR World",
    "ts": 1778838054
  },
  {
    "key": "ukraine--missile-strike--kyiv",
    "source": "GN: Strike Attack",
    "ts": 1778838054
  },
  {
    "key": "india--quake--kolkata",
    "source": "GN: Earthquake",
    "ts": 1778838054
  },
  {
    "key": "india--storm--uttar-pradesh",
    "source": "GN: Breaking News",
    "ts": 1778838056
  },
  {
    "key": "india--hostage--manipur",
    "source": "GN: Hostage",
    "ts": 1778838059
  },
  {
    "key": "oman--attack--indian-vessel",
    "source": "GN: Terror Attack",
    "ts": 1778838059
  }
]