[
  {
    "key": "uk--outbreak--berkshire",
    "source": "Times of India World",
    "ts": 1778866250
  },
  {
    "key": "uganda--outbreak--ebola",
    "source": "GN: Outbreak",
    "ts": 1778866250
  },
  {
    "key": "usa--explosion--maine",
    "source": "GN: Explosion",
    "ts": 1778866253
  },
  {
    "key": "usa--crash--akron",
    "source": "GN: Plane Crash",
    "ts": 1778866253
  },
  {
    "key": "ukraine--attack--kyiv",
    "source": "GN: Strike Attack",
    "ts": 1778866253
  },
  {
    "key": "usa--explosion--maine-lumber-mill",
    "source": "GN: Explosion",
    "ts": 1778866853
  },
  {
    "key": "usa--terrorism-charges--iraqi-national",
    "source": "GN: Breaking News",
    "ts": 1778867454
  },
  {
    "key": "gaza--airstrike--gaza-city",
    "source": "GN: Strike Attack",
    "ts": 1778867457
  },
  {
    "key": "usa--shooting--buckeye-arizona",
    "source": "GN: Breaking News",
    "ts": 1778867459
  },
  {
    "key": "ukraine--airstrike--kyiv",
    "source": "GN: Strike Attack",
    "ts": 1778867459
  },
  {
    "key": "palestine--airstrike--gaza-city",
    "source": "TASS English",
    "ts": 1778868056
  },
  {
    "key": "palestine--airstrike--gaza-city",
    "source": "GN: Strike Attack",
    "ts": 1778868060
  },
  {
    "key": "somalia--hostage--pirate-crew",
    "source": "GN: Hostage",
    "ts": 1778868060
  },
  {
    "key": "drc--outbreak--ebola",
    "source": "GN: Outbreak",
    "ts": 1778868062
  },
  {
    "key": "ukraine--conflict--kyiv",
    "source": "Al Jazeera",
    "ts": 1778868062
  },
  {
    "key": "gaza--airstrike--hamas-leader",
    "source": "Straits Times World",
    "ts": 1778868662
  },
  {
    "key": "none",
    "source": "GN: Outbreak",
    "ts": 1778868662
  },
  {
    "key": "drc--outbreak--ebola",
    "source": "GN: Outbreak",
    "ts": 1778868666
  },
  {
    "key": "ukraine--airstrike--kyiv",
    "source": "GN: Strike Attack",
    "ts": 1778868666
  },
  {
    "key": "ukraine--attack--kyiv",
    "source": "GN: Strike Attack",
    "ts": 1778868666
  },
  {
    "key": "usa--crash--akron",
    "source": "GN: Plane Crash",
    "ts": 1778868666
  },
  {
    "key": "gaza--airstrike--gaza-city",
    "source": "Jerusalem Post",
    "ts": 1778869252
  },
  {
    "key": "canada--fire--alberta",
    "source": "GN: Wildfire",
    "ts": 1778869252
  },
  {
    "key": "usa--explosion--maine",
    "source": "GN: Explosion",
    "ts": 1778869252
  },
  {
    "key": "gaza--airstrike--gaza-city",
    "source": "GN: Strike Attack",
    "ts": 1778869252
  }
]