{
  "2c1ca52eb48a86f3": {
    "ts": 1782393229,
    "words": [
      "current",
      "declare",
      "end",
      "global",
      "hantavirus",
      "july",
      "officially",
      "outbreak",
      "set",
      "who"
    ]
  },
  "412d64d371639961": {
    "ts": 1782340793,
    "words": [
      "american",
      "among",
      "cases",
      "concluding",
      "day",
      "ended",
      "final",
      "hantavirus",
      "hhs",
      "hondius",
      "its",
      "june",
      "monitoring",
      "mvhondius",
      "officially",
      "passengers",
      "period",
      "response",
      "travelers"
    ]
  },
  "5a4a18c3e4f0252e": {
    "ts": 1782321813,
    "words": [
      "actively",
      "congo",
      "democratic",
      "ebola",
      "fast",
      "health",
      "moving",
      "outbreak",
      "remains",
      "republic",
      "threat",
      "under",
      "warns",
      "who",
      "workers"
    ]
  },
  "66fda03128eb5783": {
    "ts": 1782403054,
    "words": [
      "100",
      "284",
      "begin",
      "bundibugyo",
      "cases",
      "confirmed",
      "congo",
      "deaths",
      "drc",
      "ebola",
      "ever",
      "exist",
      "largest",
      "next",
      "outbreak",
      "recorded",
      "surpassed",
      "treatments",
      "trials",
      "uganda",
      "vaccines",
      "week"
    ]
  },
  "b90f61657ccc9171": {
    "ts": 1782467757,
    "words": [
      "chance",
      "continues",
      "diseases",
      "drc",
      "ebola",
      "ever",
      "expand",
      "fastest",
      "infectious",
      "lancet",
      "modelling",
      "outbreak",
      "published",
      "puts",
      "reaching",
      "recorded",
      "south",
      "southsudan",
      "sudan",
      "uganda",
      "weeks",
      "who",
      "within"
    ]
  },
  "bd46fbb06b178892": {
    "ts": 1782345046,
    "words": [
      "118",
      "291",
      "408",
      "bringing",
      "cases",
      "confirmed",
      "congo",
      "deaths",
      "ebola",
      "hospitalized",
      "hours",
      "new",
      "now",
      "past",
      "patients",
      "recorded",
      "stand",
      "toll",
      "total"
    ]
  },
  "c1b29be4cfee1316": {
    "ts": 1782374322,
    "words": [
      "bundibugyo",
      "delivered",
      "ebola",
      "kits",
      "korea",
      "north",
      "pyongyang",
      "request",
      "rospotrebnadzor",
      "russia",
      "strain",
      "test"
    ]
  },
  "eb7ce071fb06d6ef": {
    "ts": 1782314046,
    "words": [
      "121",
      "aboard",
      "andes",
      "apr",
      "argentina",
      "crew",
      "cruise",
      "departed",
      "dutch",
      "hantavirus",
      "hondius",
      "infected",
      "killing",
      "netherlands",
      "outbreak",
      "passengers",
      "ship",
      "ushuaia",
      "vessel"
    ]
  },
  "f2a3657cebffa3cd": {
    "ts": 1782425416,
    "words": [
      "bleeding",
      "bundibugyo",
      "bvd",
      "cases",
      "confirmed",
      "congo",
      "current",
      "departure",
      "disease",
      "ebola",
      "found",
      "hemorrhagic",
      "nejm",
      "outbreak",
      "outbreaks",
      "preliminary",
      "presentation",
      "rate",
      "sharp",
      "showed",
      "signs",
      "study",
      "typical",
      "virus"
    ]
  }
}