{
  "438b928f50119aa4": {
    "ts": 1780954249,
    "words": [
      "515",
      "544",
      "550",
      "bundibugyo",
      "bunia",
      "cases",
      "dead",
      "deaths",
      "drc",
      "ebola",
      "epicenter",
      "healthcare",
      "infected",
      "ituri",
      "outbreak",
      "province",
      "surpasses",
      "uganda",
      "workers"
    ]
  },
  "57f918bf6bebabe5": {
    "ts": 1781049087,
    "words": [
      "former",
      "hondius",
      "including",
      "kornfeld",
      "left",
      "more",
      "national",
      "nebraska",
      "omaha",
      "oncologist",
      "passengers",
      "quarantine",
      "quarantined",
      "remain",
      "retired",
      "stephen",
      "unit",
      "unmc",
      "weeks"
    ]
  },
  "9b8a8ef27c25e654": {
    "ts": 1781095502,
    "words": [
      "000",
      "792",
      "active",
      "authorities",
      "border",
      "cases",
      "concerns",
      "confirmed",
      "contacts",
      "cross",
      "district",
      "ebola",
      "face",
      "health",
      "heightened",
      "kasese",
      "monitoring",
      "older",
      "residents",
      "risk",
      "spread",
      "uganda",
      "where"
    ]
  },
  "9e7fe1e83de37445": {
    "ts": 1781029985,
    "words": [
      "363",
      "available",
      "bundibugyo",
      "case",
      "cases",
      "confirmed",
      "congo",
      "death",
      "deaths",
      "drc",
      "ebola",
      "numbers",
      "outbreak",
      "rate",
      "reached",
      "rise",
      "uganda",
      "unprecedented",
      "vaccine",
      "virus"
    ]
  },
  "b8bb9401a5ea9770": {
    "ts": 1781001969,
    "words": [
      "americans",
      "bed",
      "centre",
      "county",
      "demonstrations",
      "disperse",
      "drc",
      "ebola",
      "fired",
      "gas",
      "intended",
      "isolation",
      "kenya",
      "killed",
      "laikipia",
      "last",
      "nanyuki",
      "opposing",
      "outbreak",
      "planned",
      "police",
      "protesters",
      "similar",
      "tear",
      "treat",
      "week"
    ]
  }
}