{
  "254dfd79ebb81e9f": {
    "ts": 1783261134,
    "words": [
      "africa",
      "chief",
      "dead",
      "declares",
      "expected",
      "france",
      "further",
      "global",
      "hantavirus",
      "hondius",
      "hospitalized",
      "infected",
      "least",
      "mvhondius",
      "officially",
      "one",
      "outbreak",
      "over",
      "patients",
      "remain",
      "says",
      "south",
      "tedros",
      "transmission",
      "two",
      "who"
    ]
  },
  "2bacd6cb673248e2": {
    "ts": 1783214919,
    "words": [
      "aboard",
      "andes",
      "argentina",
      "canary",
      "confirms",
      "cruise",
      "died",
      "hantavirus",
      "involving",
      "islands",
      "outbreak",
      "passengers",
      "person",
      "ship",
      "spreads",
      "strain",
      "traveling",
      "which",
      "who"
    ]
  },
  "2bb4962e2eab89ce": {
    "ts": 1783240425,
    "words": [
      "492",
      "528",
      "cases",
      "confirmed",
      "congo",
      "day",
      "death",
      "ebola",
      "fatalities",
      "infections",
      "new",
      "now",
      "reaches",
      "single",
      "stand",
      "toll"
    ]
  },
  "447154041d339039": {
    "ts": 1783274195,
    "words": [
      "cases",
      "congo",
      "democratic",
      "ebola",
      "republic",
      "rising"
    ]
  },
  "499b5244ad5068ba": {
    "ts": 1783150733,
    "words": [
      "473",
      "500",
      "502",
      "cases",
      "confirmed",
      "congo",
      "dead",
      "ebola",
      "fatality",
      "ituri",
      "july",
      "outbreak",
      "province",
      "rate",
      "surpassed"
    ]
  },
  "5a0ade67601694cb": {
    "ts": 1783193156,
    "words": [
      "aboard",
      "andes",
      "argentina",
      "atlantic",
      "contact",
      "died",
      "disembarked",
      "evacuated",
      "hantavirus",
      "helena",
      "hit",
      "hondius",
      "ill",
      "left",
      "mvhondius",
      "netherlands",
      "now",
      "passengers",
      "seriously",
      "ship",
      "since",
      "south",
      "strain",
      "tracing",
      "without"
    ]
  },
  "8090806532cf0064": {
    "ts": 1783179840,
    "words": [
      "air",
      "detected",
      "discharged",
      "doctor",
      "drc",
      "ebola",
      "ever",
      "first",
      "flew",
      "flight",
      "france",
      "hospital",
      "june",
      "paris",
      "patient",
      "recovered",
      "who"
    ]
  },
  "eda70f8251a59c79": {
    "ts": 1783214915,
    "words": [
      "000",
      "cases",
      "concentrated",
      "confirmed",
      "congo",
      "drc",
      "ebola",
      "ituri",
      "kivu",
      "largest",
      "making",
      "north",
      "northeastern",
      "ongoing",
      "outbreak",
      "provinces",
      "record",
      "second",
      "south",
      "surpassed"
    ]
  },
  "ff1543e6eb1e55a2": {
    "ts": 1783150736,
    "words": [
      "aboard",
      "cruise",
      "deadly",
      "declared",
      "global",
      "hantavirus",
      "hondius",
      "mvhondius",
      "officially",
      "outbreak",
      "over",
      "ship",
      "who"
    ]
  }
}